poopy
ez_setup
