Metadata-Version: 1.1
Name: poopy
Version: 0.2.5
Summary: Pure Python implementation of Map-Reduce over AMQP
Home-page: http://poopy.jbcabral.org
Author: JuanBC
Author-email: jbc.develop@gmail.com
License: WISKEY-WARE
Keywords: amqp rabitmq map reduce
Platform: UNKNOWN
Classifier: Topic :: Utilities
Classifier: License :: OSI Approved :: BSD License
Classifier: Programming Language :: Python :: 2
